MANIFEST.in
setup.py
recast_flask_frontend.egg-info/PKG-INFO
recast_flask_frontend.egg-info/SOURCES.txt
recast_flask_frontend.egg-info/dependency_links.txt
recast_flask_frontend.egg-info/entry_points.txt
recast_flask_frontend.egg-info/requires.txt
recast_flask_frontend.egg-info/top_level.txt
recastfrontend/__init__.py
recastfrontend/admincli.py
recastfrontend/asynctasks.py
recastfrontend/celeryapp.py
recastfrontend/celeryconfig.py
recastfrontend/flaskconfig.py
recastfrontend/forms.py
recastfrontend/frontendcli.py
recastfrontend/frontendconfig.py
recastfrontend/populate_db.py
recastfrontend/psearch.py
recastfrontend/server.py
recastfrontend/synctasks.py
recastfrontend/resources/defaultconfig.yaml
recastfrontend/resources/testdb_data/GGMmap.txt
recastfrontend/static/base.css
recastfrontend/static/bootstrap.min.css
recastfrontend/static/card.css
recastfrontend/static/home.css
recastfrontend/static/nprogress.css
recastfrontend/static/nprogress.js
recastfrontend/static/recast.js
recastfrontend/static/spin.min.js
recastfrontend/static/style.css
recastfrontend/static/sweetalert.css
recastfrontend/static/sweetalert.min.js
recastfrontend/static/img/diana-hep-logo.svg
recastfrontend/static/img/recast-atom.svg
recastfrontend/static/img/recast-logo-mark.svg
recastfrontend/static/img/recast-logo.svg
recastfrontend/static/img/recast-review.svg
recastfrontend/static/img/recast-submit.svg
recastfrontend/static/img/recast-subscribe.svg
recastfrontend/static/img/recast.ico
recastfrontend/static/img/partner-funders/cap.svg
recastfrontend/static/img/partner-funders/daspos.png
recastfrontend/static/img/partner-funders/moore_foundation.jpg
recastfrontend/static/img/partner-funders/nsf.gif
recastfrontend/static/img/partner-funders/sloan.png
recastfrontend/templates/404.html
recastfrontend/templates/about.html
recastfrontend/templates/analyses.html
recastfrontend/templates/analyses_views.html
recastfrontend/templates/analysis-search-results.html
recastfrontend/templates/analysis.html
recastfrontend/templates/analysis_form.html
recastfrontend/templates/base.html
recastfrontend/templates/basic_response_data.html
recastfrontend/templates/contact.html
recastfrontend/templates/footer.html
recastfrontend/templates/form.html
