Metadata-Version: 1.0
Name: recast-flask-frontend
Version: 0.1.0
Summary: new frontend for the RECAST project
Home-page: https://github.com/lukasheinrich/recast-newfrontend
Author: Lukas Heinrich
Author-email: lukas.heinrich@cern.ch
License: UNKNOWN
Platform: UNKNOWN
